easyspider/__init__.py
easyspider/requirements.txt
easyspider/commands/__init__.py
easyspider/commands/bench.py
easyspider/commands/check.py
easyspider/commands/crawl.py
easyspider/commands/edit.py
easyspider/commands/fetch.py
easyspider/commands/genspider.py
easyspider/commands/list.py
easyspider/commands/parse.py
easyspider/commands/runspider.py
easyspider/commands/settings.py
easyspider/commands/shell.py
easyspider/commands/startproject.py
easyspider/commands/version.py
easyspider/commands/view.py
easyspider/core/__init__.py
easyspider/core/cmdline.py
easyspider/core/easyEngine.py
easyspider/core/easyItemPipelineManager.py
easyspider/core/easyScraper.py
easyspider/core/easycrawler.py
easyspider/core/easydupefilter.py
easyspider/core/easyqueue.py
easyspider/core/easyscheduler.py
easyspider/core/spiderloader.py
easyspider/core/statscollectors.py
easyspider/etl/DBService.py
easyspider/etl/__init__.py
easyspider/etl/base_etl.py
easyspider/etl/base_mongo_result_2_csv.py
easyspider/etl/base_mongo_result_2_mysql.py
easyspider/etl/base_mongo_start_url_2_redis.py
easyspider/etl/extract.py
easyspider/middlewares/__init__.py
easyspider/middlewares/antiSpider.py
easyspider/middlewares/httperror.py
easyspider/middlewares/redirect.py
easyspider/middlewares/retry.py
easyspider/middlewares/useragent.py
easyspider/monitor/__init__.py
easyspider/monitor/base_log_monitor.py
easyspider/monitor/log_monitor.cfg
easyspider/monitor/log_monitor_server.py
easyspider/monitor/result_monitor_base.py
easyspider/pipelines/__init__.py
easyspider/pipelines/commonBasepipeline.py
easyspider/pipelines/commonMongopipeline.py
easyspider/pipelines/commonMysqlpipeline.py
easyspider/pipelines/commonpipeline.py
easyspider/settings/__init__.py
easyspider/settings/settings.py
easyspider/spiders/__init__.py
easyspider/spiders/easyCrawlSpider.py
easyspider/template_dir/scrapy.cfg
easyspider/template_dir/crawler/__init__.py
easyspider/template_dir/crawler/settings.py
easyspider-1.9.1.dist-info/METADATA
easyspider-1.9.1.dist-info/WHEEL
easyspider-1.9.1.dist-info/entry_points.txt
easyspider-1.9.1.dist-info/RECORD
